example
tinymcewrapper
