Metadata-Version: 1.0
Name: django-tinymcewrapper
Version: 0.4.2
Summary: django-tinymcewrapper allows you to easily add tinymce widgets to other apps admin forms without modification of the other app.
Home-page: http://callowayproject.com/
Author: coordt
Author-email: coreyoordt@gmail.com
License: UNKNOWN
Platform: UNKNOWN
Classifier: License :: OSI Approved :: Apache Software License
Classifier: Framework :: Django
